{
  "divinerpg:overworld/root": {
    "criteria": {
      "divinerpg": "2020-12-17 15:55:20 +0100"
    },
    "done": true
  },
  "aoa3:overworld/by_the_books": {
    "criteria": {
      "legitimate": "2020-12-17 15:55:11 +0100"
    },
    "done": true
  },
  "iceandfire:iceandfire/root": {
    "criteria": {
      "tick": "2020-12-17 15:55:25 +0100"
    },
    "done": true
  },
  "biomesoplenty:biomesoplenty/all_biomes": {
    "criteria": {
      "shrubland": "2020-12-17 15:55:20 +0100"
    },
    "done": false
  },
  "mowziesmobs:root": {
    "criteria": {
      "custom_test_name": "2020-12-17 15:55:25 +0100"
    },
    "done": true
  },
  "aoa3:overworld/root": {
    "criteria": {
      "playerjoin": "2020-12-17 15:55:11 +0100"
    },
    "done": true
  },
  "mysticalworld:root": {
    "criteria": {
      "auto": "2020-12-17 15:55:20 +0100"
    },
    "done": true
  }
}